[{"hoarding": {"h_res": 800, "v_res": 600, "height": 10, "width": 12, "cost": 20000.0, "display_type": 2, "address": {"city": {"id": 75, "name": "Pune"}, "state": {"id": 15, "name": "Maharashtra"}, "address": "Abhinav Chowk", "geo_location": "18.505405, 73.853738", "country": {"id": 1, "name": "India"}}, "cost_cycle": 3, "last_update": "2017-06-21T22:14:03.493109", "id": 7}, "campaign": {"resource": "http://192.168.0.107:8000/static/uploads/hyundai-creta-low.mp4", "name": "Hyundai-Creta", "content_status": 0, "creation_date": "2017-04-22T15:23:46.974204", "from_date": "2017-05-01", "to_date": "2017-05-31", "id": 19}}, {"hoarding": {"h_res": 800, "v_res": 600, "height": 10, "width": 12, "cost": 20000.0, "display_type": 2, "address": {"city": {"id": 75, "name": "Pune"}, "state": {"id": 15, "name": "Maharashtra"}, "address": "Abhinav Chowk", "geo_location": "18.505405, 73.853738", "country": {"id": 1, "name": "India"}}, "cost_cycle": 3, "last_update": "2017-06-21T22:14:03.493109", "id": 7}, "campaign": {"resource": "http://192.168.0.107:8000/var/www/media/flexplex/samsung1.mp4", "name": "20june-test", "content_status": 0, "creation_date": "2017-06-20T22:14:03.318243", "from_date": "2017-07-01", "to_date": "2017-07-31", "id": 30}}]